setup.py
python_cli_runner.egg-info/PKG-INFO
python_cli_runner.egg-info/SOURCES.txt
python_cli_runner.egg-info/dependency_links.txt
python_cli_runner.egg-info/requires.txt
python_cli_runner.egg-info/top_level.txt
src/cli_runner/__init__.py
src/cli_runner/base.py
src/cli_runner/discover.py
src/cli_runner/loader.py
src/cli_runner/tools.py