Metadata-Version: 1.0
Name: python-cli-runner
Version: 0.0.4
Summary: Toolkit that organize multiple entry points of your codebase with Docopt powerful.
Home-page: https://github.com/alexey-grom/python-cli-runner
Author: alxgrmv@gmail.com
Author-email: UNKNOWN
License: UNKNOWN
Platform: UNKNOWN
